<annotation>
	<folder>Grayscale</folder>
	<filename>l2 (110).jpg</filename>
	<path>D:\Haz Mat\Projects\Safety\Grayscale\l2 (110).jpg</path>
	<source>
		<database>Unknown</database>
	</source>
	<size>
		<width>1920</width>
		<height>1280</height>
		<depth>1</depth>
	</size>
	<segmented>0</segmented>
	<object>
		<name>leopard</name>
		<pose>Unspecified</pose>
		<truncated>0</truncated>
		<difficult>0</difficult>
		<bndbox>
			<xmin>649</xmin>
			<ymin>327</ymin>
			<xmax>1813</xmax>
			<ymax>1082</ymax>
		</bndbox>
	</object>
	<object>
		<name>leopard</name>
		<pose>Unspecified</pose>
		<truncated>0</truncated>
		<difficult>0</difficult>
		<bndbox>
			<xmin>670</xmin>
			<ymin>341</ymin>
			<xmax>1579</xmax>
			<ymax>885</ymax>
		</bndbox>
	</object>
	<object>
		<name>leopard</name>
		<pose>Unspecified</pose>
		<truncated>0</truncated>
		<difficult>0</difficult>
		<bndbox>
			<xmin>628</xmin>
			<ymin>345</ymin>
			<xmax>1591</xmax>
			<ymax>974</ymax>
		</bndbox>
	</object>
</annotation>
